src/__init__.py
test/__init__.py
SMSONAR-0.0.2.dist-info/LICENSE.txt
SMSONAR-0.0.2.dist-info/METADATA
SMSONAR-0.0.2.dist-info/WHEEL
SMSONAR-0.0.2.dist-info/top_level.txt
SMSONAR-0.0.2.dist-info/RECORD
