Metadata-Version: 2.1
Name: SMSONAR
Version: 0.0.2
Summary: Sound Metrics SONARs files software development kit     (SDK) for reading and writing SONAR files.
Home-page: https://github.com/minamaged113/SMSONAR
Author: Mina Gabriel
Author-email: minamaged113@gmail.com
License: MIT
Platform: UNKNOWN
Classifier: Programming Language :: Python :: 3
Classifier: License :: OSI Approved :: MIT License
Classifier: Operating System :: OS Independent
